torchmenu/Home.py
torchmenu/__init__.py
torchmenu/__version__.py
torchmenu/cli.py
torchmenu/settings.yaml
torchmenu/api/__init__.py
torchmenu/api/model.py
torchmenu/api/torchserve.py
torchmenu/components/__init__.py
torchmenu/components/sidebar.py
torchmenu/components/status.py
torchmenu-0.1.2.dist-info/LICENSE
torchmenu-0.1.2.dist-info/METADATA
torchmenu-0.1.2.dist-info/WHEEL
torchmenu-0.1.2.dist-info/entry_points.txt
torchmenu-0.1.2.dist-info/top_level.txt
torchmenu-0.1.2.dist-info/RECORD
