Metadata-Version: 2.1
Name: torchmenu
Version: 0.1.2
Summary: TorchServe GUI
Home-page: https://github.com/williamcorsel/TorchMenu
Author: William Corsel
License: Apache License 2.0
Requires-Python: >=3.10
License-File: LICENSE
Requires-Dist: streamlit ==1.27.0
Requires-Dist: httpx ==0.25.0
Requires-Dist: pydantic ==2.3.0
Provides-Extra: dev
Requires-Dist: pre-commit ; extra == 'dev'
Requires-Dist: flake8 ; extra == 'dev'
